pantarei/__init__.py
pantarei/backends.py
pantarei/cache.py
pantarei/cli.py
pantarei/core.py
pantarei/database.py
pantarei/helpers.py
pantarei/hooks.py
pantarei/parallel.py
pantarei/parsers.py
pantarei/reports.py
pantarei/scheduler.py
pantarei/task.py
pantarei-0.10.0.dist-info/licenses/LICENSE
pantarei-0.10.0.dist-info/METADATA
pantarei-0.10.0.dist-info/WHEEL
pantarei-0.10.0.dist-info/entry_points.txt
pantarei-0.10.0.dist-info/top_level.txt
pantarei-0.10.0.dist-info/RECORD
