Metadata-Version: 2.4
Name: pantarei
Version: 0.10.0
Summary: A general-purpose workflow manager
Author-email: Daniele Coslovich <daniele.coslovich@umontpellier.fr>
License: GPLv3
Project-URL: repository, https://framagit.org/coslo/pantarei
Project-URL: homepage, https://framagit.org/coslo/pantarei
Project-URL: documentation, https://coslo.frama.io/pantarei
Classifier: License :: OSI Approved :: GNU General Public License v3 (GPLv3)
Classifier: Programming Language :: Python :: 3
Classifier: Development Status :: 5 - Production/Stable
Requires-Python: >=3.8
License-File: LICENSE
Requires-Dist: numpy
Requires-Dist: tinydb
Requires-Dist: dill
Requires-Dist: pyyaml
Dynamic: license-file
